ztl/__init__.py
ztl/core/__init__.py
ztl/core/client.py
ztl/core/protocol.py
ztl/core/server.py
ztl/core/task.py
ztl/example/__init__.py
ztl/example/simple_client.py
ztl/example/simple_server.py
ztl/example/task_client.py
ztl/example/task_server.py
ztl/script/__init__.py
ztl/script/run_script.py
ztl-0.0.6.data/scripts/run_script.py
ztl-0.0.6.data/scripts/simple_client.py
ztl-0.0.6.data/scripts/simple_server.py
ztl-0.0.6.data/scripts/task_client.py
ztl-0.0.6.data/scripts/task_server.py
ztl-0.0.6.dist-info/licenses/LICENSE
ztl-0.0.6.dist-info/METADATA
ztl-0.0.6.dist-info/WHEEL
ztl-0.0.6.dist-info/entry_points.txt
ztl-0.0.6.dist-info/top_level.txt
ztl-0.0.6.dist-info/RECORD
