Metadata-Version: 2.4
Name: ztl
Version: 0.0.6
Summary: A thin library relying on zmq to dispatch tasks
Home-page: https://gitlab.com/robothouse/rh-user/ztl/
Author: Patrick Holthaus
Author-email: Patrick Holthaus <patrick.holthaus@googlemail.com>
License: BSD 2-Clause License
Project-URL: Homepage, https://gitlab.com/robothouse/rh-user/ztl/
Project-URL: Bug Tracker, https://gitlab.com/robothouse/rh-user/ztl/issues/
Classifier: Programming Language :: Python :: 3
Classifier: License :: OSI Approved :: BSD License
Classifier: Operating System :: OS Independent
Requires-Python: >=3.7
License-File: LICENSE
Requires-Dist: oyaml
Requires-Dist: pyzmq
Requires-Dist: pytest
Requires-Dist: pytest-xprocess
Dynamic: author
Dynamic: home-page
Dynamic: license-file
